verilog-vhdl/test/ADC_ratio/ADC_ratio.srcs/sources_1/new/adc_ratio.v
`timescale 1ns / 1ps
//////////////////////////////////////////////////////////////////////////////////
// Company: 
// Engineer: 
// 
// Create Date: 11/26/2025 11:55:19 AM
// Design Name: 
// Module Name: adc_ratio
// Project Name: 
// Target Devices: 
// Tool Versions: 
// Description: 
// 
// Dependencies: 
// 
// Revision:
// Revision 0.01 - File Created
// Additional Comments:
// 
//////////////////////////////////////////////////////////////////////////////////


module adc_ratio(
input clk,
input wire [13:0]adc, 
output reg [14:0] dac
    );
    wire [14:0] adc_val = (adc << 1);
    reg flag;
    always@(posedge clk) begin
        flag <= (adc_val[14] ~^ adc_val[12]);
        if (flag  == 1'b1 && adc == 14'h3fff) begin
            dac <= 15'h3fff;
        end
        else if( flag == 1'b1 && adc == 14'h0000)begin
            dac <= 15'h0000;
        end
        else begin
        dac <= adc_val;
        end
    end 
    
endmodule

verilog-vhdl/test/ADC_ratio/ADC_ratio.srcs/sim_1/new/sim_adc.v
module tb_adc_ratio;

    // Declare signals for the testbench
    reg clk;
    reg [13:0] adc;
    wire [14:0] dac;
    wire flag; // 'flag' must be added as an output to your main module to monitor it here

    // Instantiate the Device Under Test (DUT)
    adc_ratio DUT (
        .clk(clk),
        .adc(adc),
        .dac(dac)
        // .flag(flag) // Uncomment this line if you add 'output reg flag' to your adc_ratio module
    );

    // 2. Generate a Clock Signal
    parameter CLK_PERIOD = 10; // 10 ns period
    initial begin
        clk = 0;
        forever #(CLK_PERIOD/2) clk = ~clk;
    end

    // 3. Generate Input Stimuli
    initial begin
        // Initialize inputs
        adc = 14'h0000; 

        // Start simulation flow
        $display("------------------------------------------------------------------");
        $display("Time (ns) | ADC Input (Hex) | DAC Output (Hex)");
        $display("------------------------------------------------------------------");
        
        // Wait a bit for initialization
        # (CLK_PERIOD * 2); 

        // --- Test Normal Operation (Valid Range) ---
        // Input a valid mid-range value (0V equivalent in offset binary)
        adc = 14'h2000; 
        # CLK_PERIOD;

        // Input a valid high value
        adc = 14'h3000; 
        # CLK_PERIOD;

        // Input a valid low value
        adc = 14'h1000; 
        # CLK_PERIOD;

        // --- Test Max Clip Condition (0x3fff) ---
        // Note the interaction depends on the previous cycle's flag state
        adc = 14'h3fff; 
        # CLK_PERIOD; 
        # CLK_PERIOD; // Check behavior over multiple cycles

        // --- Test Min Clip Condition (0x0000) ---
        adc = 14'h0000; 
        # CLK_PERIOD;
        # CLK_PERIOD; // Check behavior over multiple cycles

        // --- Return to Normal Operation ---
        adc = 14'h2500; // A new valid value
        # CLK_PERIOD;

        // 4. Monitor and End Simulation
        $monitor("%0d          | %h              | %h               ", $time, adc, dac);
        
        # (CLK_PERIOD * 4); // Run for a few more cycles
        $display("------------------------------------------------------------------");
        $display("Simulation finished.");
        $finish; // System task to end the simulation
    end

    // Optional: Dump waveforms for visualization (e.g., using GTKWave)
    initial begin
        $dumpfile("adc_waveform.vcd");
        $dumpvars(0, tb_adc_ratio);
    end

endmodule

verilog-vhdl/test/ADC_ratio/ADC_ratio.sim/sim_1/behav/xsim/adc_waveform.vcd
$date
   Wed Nov 26 13:15:09 2025
$end
$version
  2017.4
$end
$timescale
  1ps
$end
$scope module tb_adc_ratio $end
$var reg 1 ! clk $end
$var reg 14 " adc [13:0] $end
$var wire 15 # dac [14:0] $end
$var wire 1 $ flag $end
$var parameter 32 % CLK_PERIOD [31:0] $end
$scope module DUT $end
$var wire 1 & clk $end
$var wire 14 ' adc [13:0] $end
$var reg 15 ( dac [14:0] $end
$var wire 15 ) adc_val [14:0] $end
$var reg 1 * flag $end
$upscope $end
$upscope $end
$enddefinitions $end
#0
$dumpvars
0!
b0 "
bx #
z$
b1010 %
0&
b0 '
bx (
b0 )
x*
$end
#5000
1!
b0 #
1&
b0 (
1*
#10000
0!
0&
#15000
1!
1&
b0 (
#20000
0!
b10000000000000 "
0&
b10000000000000 '
b100000000000000 )
#25000
1!
b100000000000000 #
1&
b100000000000000 (
0*
#30000
0!
b11000000000000 "
0&
b11000000000000 '
b110000000000000 )
#35000
1!
b110000000000000 #
1&
b110000000000000 (
#40000
0!
b1000000000000 "
0&
b1000000000000 '
b10000000000000 )
#45000
1!
b10000000000000 #
1&
b10000000000000 (
1*
#50000
0!
b11111111111111 "
0&
b11111111111111 '
b111111111111110 )
#55000
1!
b11111111111111 #
1&
b11111111111111 (
#60000
0!
0&
#65000
1!
1&
b11111111111111 (
#70000
0!
b0 "
0&
b0 '
b0 )
#75000
1!
b0 #
1&
b0 (
#80000
0!
0&
#85000
1!
1&
b0 (
#90000
0!
b10010100000000 "
0&
b10010100000000 '
b100101000000000 )
#95000
1!
b100101000000000 #
1&
b100101000000000 (
0*
#100000
0!
0&
#105000
1!
1&
b100101000000000 (
#110000
0!
0&
#115000
1!
1&
b100101000000000 (
#120000
0!
0&
#125000
1!
1&
b100101000000000 (
#130000
0!
0&
#135000
1!
1&
b100101000000000 (
